race_report/__init__.py
race_report/cli.py
race_report/report.py
task_6_report-0.4.3.dist-info/licenses/LICENSE
task_6_report-0.4.3.dist-info/METADATA
task_6_report-0.4.3.dist-info/WHEEL
task_6_report-0.4.3.dist-info/entry_points.txt
task_6_report-0.4.3.dist-info/top_level.txt
task_6_report-0.4.3.dist-info/RECORD
