Metadata-Version: 2.4
Name: task_6_report
Version: 0.4.3
Summary: Аналізатор гонки F1
Author-email: Yurii_Step <step.crypt@email.com>
License: MIT
Requires-Python: >=3.9
License-File: LICENSE
Dynamic: license-file
